main.py
iflow_mcp_python_mcp_sandbox-0.1.1.dist-info/licenses/LICENSE
mcp_sandbox/__init__.py
mcp_sandbox/models.py
iflow_mcp_python_mcp_sandbox-0.1.1.dist-info/METADATA
iflow_mcp_python_mcp_sandbox-0.1.1.dist-info/WHEEL
iflow_mcp_python_mcp_sandbox-0.1.1.dist-info/entry_points.txt
iflow_mcp_python_mcp_sandbox-0.1.1.dist-info/top_level.txt
iflow_mcp_python_mcp_sandbox-0.1.1.dist-info/RECORD
