Metadata-Version: 2.4
Name: iflow-mcp_python-mcp-sandbox
Version: 0.1.1
Summary: Safe sandboxes for llms
Requires-Python: >=3.12
License-File: LICENSE
Requires-Dist: docker>=7.1.0
Requires-Dist: fastapi>=0.115.12
Requires-Dist: fastmcp>=2.2.0
Requires-Dist: passlib[bcrypt]>=1.7.4
Requires-Dist: pydantic[email]>=2.11.3
Requires-Dist: python-jose[cryptography]>=3.4.0
Requires-Dist: python-multipart>=0.0.20
Requires-Dist: ruff>=0.11.6
Requires-Dist: tomli>=2.2.1
Dynamic: license-file
